{
  "date": "2025-03-13",
  "projects": {
    "termonied_testador": {
      "totalLinesAdded": 38,
      "totalLinesRemoved": 0,
      "totalActiveTime": 3,
      "files": {
        "/Users/admin/Library/Application Support/Code/User/settings.json": [
          {
            "timestamp": "2025-03-13T15:23:11.515Z",
            "fileName": "/Users/admin/Library/Application Support/Code/User/settings.json",
            "fileType": ".json",
            "linesAdded": 35,
            "linesRemoved": 0,
            "projectName": "termonied_testador",
            "content": {
              "added": [],
              "removed": []
            },
            "duration": 0,
            "language": "json"
          },
          {
            "timestamp": "2025-03-13T15:23:16.803Z",
            "fileName": "/Users/admin/Library/Application Support/Code/User/settings.json",
            "fileType": ".json",
            "linesAdded": 1,
            "linesRemoved": 0,
            "projectName": "termonied_testador",
            "content": {
              "added": [],
              "removed": []
            },
            "duration": 1,
            "language": "json"
          },
          {
            "timestamp": "2025-03-13T15:23:18.437Z",
            "fileName": "/Users/admin/Library/Application Support/Code/User/settings.json",
            "fileType": ".json",
            "linesAdded": 1,
            "linesRemoved": 0,
            "projectName": "termonied_testador",
            "content": {
              "added": [],
              "removed": []
            },
            "duration": 1,
            "language": "json"
          },
          {
            "timestamp": "2025-03-13T15:23:19.964Z",
            "fileName": "/Users/admin/Library/Application Support/Code/User/settings.json",
            "fileType": ".json",
            "linesAdded": 1,
            "linesRemoved": 0,
            "projectName": "termonied_testador",
            "content": {
              "added": [],
              "removed": []
            },
            "duration": 1,
            "language": "json"
          }
        ]
      },
      "languageStats": {
        "json": 3
      },
      "changeFrequency": {
        "12": 3
      },
      "topFiles": [
        "/Users/admin/Library/Application Support/Code/User/settings.json"
      ],
      "averageChangeSize": 9.5
    },
    "termonied-web": {
      "totalLinesAdded": 89,
      "totalLinesRemoved": 0,
      "totalActiveTime": 2,
      "files": {
        "/Users/admin/Development/Clients/TermoNied/termonied-web/components/DataTable/SelectCell.tsx": [
          {
            "timestamp": "2025-03-13T15:27:29.010Z",
            "fileName": "/Users/admin/Development/Clients/TermoNied/termonied-web/components/DataTable/SelectCell.tsx",
            "fileType": ".tsx",
            "linesAdded": 54,
            "linesRemoved": 0,
            "projectName": "termonied-web",
            "content": {
              "added": [],
              "removed": []
            },
            "duration": 0,
            "language": "tsx"
          },
          {
            "timestamp": "2025-03-13T15:28:52.786Z",
            "fileName": "/Users/admin/Development/Clients/TermoNied/termonied-web/components/DataTable/SelectCell.tsx",
            "fileType": ".tsx",
            "linesAdded": 35,
            "linesRemoved": 0,
            "projectName": "termonied-web",
            "content": {
              "added": [],
              "removed": []
            },
            "duration": 2,
            "language": "tsx"
          }
        ]
      },
      "languageStats": {
        "tsx": 0
      },
      "changeFrequency": {
        "12": 0
      },
      "topFiles": [
        "/Users/admin/Development/Clients/TermoNied/termonied-web/components/DataTable/SelectCell.tsx"
      ],
      "averageChangeSize": 54
    },
    "WorkValut": {
      "totalLinesAdded": 44,
      "totalLinesRemoved": 0,
      "totalActiveTime": 0,
      "files": {
        "/Users/admin/Library/Application Support/Code/User/settings.json": [
          {
            "timestamp": "2025-03-13T16:47:54.148Z",
            "fileName": "/Users/admin/Library/Application Support/Code/User/settings.json",
            "fileType": ".json",
            "linesAdded": 44,
            "linesRemoved": 0,
            "projectName": "WorkValut",
            "content": {
              "added": [],
              "removed": []
            },
            "duration": 0,
            "language": "json"
          }
        ]
      },
      "languageStats": {
        "json": 0
      },
      "changeFrequency": {
        "13": 0
      },
      "topFiles": [
        "/Users/admin/Library/Application Support/Code/User/settings.json"
      ],
      "averageChangeSize": 44
    },
    "lumine-web": {
      "totalLinesAdded": 673,
      "totalLinesRemoved": 0,
      "totalActiveTime": 5,
      "files": {
        "/Users/admin/Development/Clients/Lumine/lumine-web/src/functions/eventTracking.ts": [
          {
            "timestamp": "2025-03-13T19:32:44.909Z",
            "fileName": "/Users/admin/Development/Clients/Lumine/lumine-web/src/functions/eventTracking.ts",
            "fileType": ".ts",
            "linesAdded": 23,
            "linesRemoved": 0,
            "projectName": "lumine-web",
            "content": {
              "added": [],
              "removed": []
            },
            "duration": 0,
            "language": "ts"
          }
        ],
        "/Users/admin/Development/Clients/Lumine/lumine-web/src/router/index.ts": [
          {
            "timestamp": "2025-03-13T19:37:23.249Z",
            "fileName": "/Users/admin/Development/Clients/Lumine/lumine-web/src/router/index.ts",
            "fileType": ".ts",
            "linesAdded": 650,
            "linesRemoved": 0,
            "projectName": "lumine-web",
            "content": {
              "added": [],
              "removed": []
            },
            "duration": 5,
            "language": "ts"
          }
        ]
      },
      "languageStats": {
        "ts": 5
      },
      "changeFrequency": {
        "16": 5
      },
      "topFiles": [
        "/Users/admin/Development/Clients/Lumine/lumine-web/src/functions/eventTracking.ts",
        "/Users/admin/Development/Clients/Lumine/lumine-web/src/router/index.ts"
      ],
      "averageChangeSize": 336.5
    }
  },
  "totalActiveTime": 3,
  "totalProjects": 1,
  "totalFiles": 1,
  "mostActiveHours": [
    12
  ],
  "mostUsedLanguages": [
    "json"
  ]
}